Metadata-Version: 2.1
Name: competencias
Version: 1.0.3
Summary: Implementação em Python de biblioteca para trabalhar com Competencias no estilo YYYYMM.
Home-page: https://github.com/lais-huol/py-competencias
Author: Kelson da Costa Medeiros
Author-email: kelson.medeiros@lais.huol.ufrn.br
License: Apache-2.0
Download-URL: https://github.com/lais-huol/py-competencias/releases/tag/1.0.3
Keywords: competencia
Platform: UNKNOWN
Classifier: Development Status :: 5 - Production/Stable
Classifier: Programming Language :: Python
Classifier: Programming Language :: Python :: 3.9
Classifier: Programming Language :: Python :: 3.10
Classifier: Programming Language :: Python :: 3.11
Classifier: Intended Audience :: Developers
Classifier: License :: OSI Approved :: Apache Software License
Classifier: Operating System :: OS Independent
Classifier: Topic :: Software Development :: Libraries
Classifier: Topic :: Software Development :: Libraries :: Python Modules
Requires-Python: >=3.9
